mira/__init__.py
mira/preferences.py
mira/adata_interface/__init__.py
mira/adata_interface/core.py
mira/adata_interface/joint.py
mira/adata_interface/lite_nite.py
mira/adata_interface/plots.py
mira/adata_interface/pseudotime.py
mira/adata_interface/regulators.py
mira/adata_interface/rp_model.py
mira/adata_interface/topic_model.py
mira/adata_interface/utils.py
mira/cli/tune-topic-model.py
mira/datasets/__init__.py
mira/datasets/datasets.py
mira/package_data/motifs/MA0001.2_AGL3.jaspar
mira/package_data/motifs/MA0002.2_RUNX1.jaspar
mira/package_data/motifs/MA0003.4_TFAP2A.jaspar
mira/package_data/motifs/MA0004.1_ARNT.jaspar
mira/package_data/motifs/MA0005.2_AG.jaspar
mira/package_data/motifs/MA0006.1_AHR::ARNT.jaspar
mira/package_data/motifs/MA0007.3_AR.jaspar
mira/package_data/motifs/MA0008.2_HAT5.jaspar
mira/package_data/motifs/MA0009.2_TBXT.jaspar
mira/package_data/motifs/MA0010.1_BR.jaspar
mira/package_data/motifs/MA0011.1_BR.VAR.2.jaspar
mira/package_data/motifs/MA0012.1_BR.VAR.3.jaspar
mira/package_data/motifs/MA0013.1_BR.VAR.4.jaspar
mira/package_data/motifs/MA0014.3_PAX5.jaspar
mira/package_data/motifs/MA0015.1_CF2.jaspar
mira/package_data/motifs/MA0016.1_USP.jaspar
mira/package_data/motifs/MA0017.2_NR2F1.jaspar
mira/package_data/motifs/MA0018.4_CREB1.jaspar
mira/package_data/motifs/MA0019.1_DDIT3::CEBPA.jaspar
mira/package_data/motifs/MA0020.1_DOF2.jaspar
mira/package_data/motifs/MA0021.1_DOF3.jaspar
mira/package_data/motifs/MA0022.1_DL.jaspar
mira/package_data/motifs/MA0023.1_DL.VAR.2.jaspar
mira/package_data/motifs/MA0024.3_E2F1.jaspar
mira/package_data/motifs/MA0025.2_NFIL3.jaspar
mira/package_data/motifs/MA0026.1_EIP74EF.jaspar
mira/package_data/motifs/MA0027.2_EN1.jaspar
mira/package_data/motifs/MA0028.2_ELK1.jaspar
mira/package_data/motifs/MA0029.1_MECOM.jaspar
mira/package_data/motifs/MA0030.1_FOXF2.jaspar
mira/package_data/motifs/MA0031.1_FOXD1.jaspar
mira/package_data/motifs/MA0032.2_FOXC1.jaspar
mira/package_data/motifs/MA0033.2_FOXL1.jaspar
mira_multiome-2.1.1.dist-info/METADATA
mira_multiome-2.1.1.dist-info/WHEEL
mira_multiome-2.1.1.dist-info/top_level.txt
mira_multiome-2.1.1.dist-info/zip-safe
mira_multiome-2.1.1.dist-info/RECORD
