Metadata-Version: 2.1
Name: mira-multiome
Version: 2.1.1
Summary: Single-cell multiomics data analysis
License: BSD3 License
Classifier: License :: OSI Approved :: BSD License
Classifier: Environment :: Console
Classifier: Intended Audience :: Developers
Classifier: Intended Audience :: Science/Research
Classifier: Natural Language :: English
Classifier: Operating System :: MacOS :: MacOS X
Classifier: Operating System :: POSIX :: Linux
Classifier: Programming Language :: Python :: 3
Classifier: Programming Language :: Python :: 3.5
Classifier: Programming Language :: Python :: 3.6
Classifier: Programming Language :: Python :: 3.7
Classifier: Programming Language :: Python :: 3.8
Classifier: Programming Language :: Python :: 3.9
Classifier: Programming Language :: Python :: 3.10
Classifier: Programming Language :: Python :: 3.11
Requires-Python: <3.12,>=3.6
Requires-Dist: torch <=2.0.0,>=1.8.0
Requires-Dist: pyro-ppl <2,>=1.5.2
Requires-Dist: networkx <=2.5,>=2.3
Requires-Dist: optuna <3,>=2.8
Requires-Dist: anndata <1,>=0.7.6
Requires-Dist: pyfaidx <1,>=0.5
Requires-Dist: matplotlib <4,>=3.7
Requires-Dist: scikit-learn <1.4,>=0.24
Requires-Dist: scipy <=1.10.2
Requires-Dist: lisa2 >=2.3.0
Requires-Dist: requests <3,>=2
Requires-Dist: mira-moods >=1.9.4.2
Requires-Dist: sqlalchemy <2
Requires-Dist: tqdm
Requires-Dist: tensorboard
Provides-Extra: docs
Requires-Dist: sphinx >=4 ; extra == 'docs'
Requires-Dist: nbsphinx ; extra == 'docs'
Requires-Dist: sphinx-panels ; extra == 'docs'
Requires-Dist: pydata-sphinx-theme ; extra == 'docs'
Requires-Dist: sphinx-copybutton ; extra == 'docs'
Requires-Dist: numpydoc ; extra == 'docs'
Requires-Dist: ipython ; extra == 'docs'
Provides-Extra: redis
Requires-Dist: redis ; extra == 'redis'
